[
  { "file": "VER_025_07.png", "figura": null, "nome": "Seggiovia (impianto di risalita)", "confidenza": "media", "scarto": false },
  { "file": "VER_025_08.png", "figura": null, "nome": "Sciatore (piste da sci)", "confidenza": "media", "scarto": false },
  { "file": "VER_025_09.png", "figura": null, "nome": "Pittogramma con vela curva rossa e verde, non identificato", "confidenza": "bassa", "scarto": false },
  { "file": "VER_025_10.png", "figura": null, "nome": "Stemma araldico su scudo verde con aquila dorata e corno", "confidenza": "bassa", "scarto": false },
  { "file": "VER_025_11.png", "figura": null, "nome": "Freccia direzionale verso l'alto", "confidenza": "media", "scarto": false },
  { "file": "VER_025_12.png", "figura": null, "nome": null, "confidenza": "alta", "scarto": true },

  { "file": "VER_027_01.png", "figura": "233", "nome": "Preavviso di intersezione con preselezione (fondo bianco urbano)", "confidenza": "media", "scarto": false },
  { "file": "VER_027_02.png", "figura": "234", "nome": "Preavviso di intersezione a frecce su strada extraurbana", "confidenza": "media", "scarto": false },
  { "file": "VER_027_03.png", "figura": "235", "nome": "Preavviso di intersezione autostradale", "confidenza": "media", "scarto": false },
  { "file": "VER_027_04.png", "figura": "236", "nome": "Preavviso di intersezione con divieto di accesso su una direzione", "confidenza": "media", "scarto": false },
  { "file": "VER_027_05.png", "figura": "237", "nome": "Preavviso di intersezione con due uscite (formato verticale)", "confidenza": "media", "scarto": false },
  { "file": "VER_027_06.png", "figura": "238", "nome": "Preavviso di intersezione con rotatoria", "confidenza": "media", "scarto": false },
  { "file": "VER_027_07.png", "figura": "239", "nome": "Preavviso di intersezione con divieto di transito ai veicoli merci", "confidenza": "media", "scarto": false },
  { "file": "VER_027_08.png", "figura": "240", "nome": "Preavviso di intersezione con passaggio a livello (fondo blu)", "confidenza": "media", "scarto": false },
  { "file": "VER_027_09.png", "figura": "241", "nome": "Segnale di preselezione (fondo bianco urbano)", "confidenza": "media", "scarto": false },
  { "file": "VER_027_10.png", "figura": "243", "nome": "Segnale di preselezione su strada extraurbana", "confidenza": "media", "scarto": false },

  { "file": "VER_029_01.png", "figura": "248", "nome": "Segnale di direzione (freccia direzionale)", "confidenza": "media", "scarto": false },
  { "file": "VER_029_02.png", "figura": "294", "nome": "Segnale di direzione turistica e di territorio", "confidenza": "media", "scarto": false },
  { "file": "VER_029_03.png", "figura": "296", "nome": "Segnale di direzione per zona industriale", "confidenza": "media", "scarto": false },
  { "file": "VER_029_04.png", "figura": "297", "nome": "Segnali di direzione per zona industriale (serie frecce)", "confidenza": "media", "scarto": false },
  { "file": "VER_029_05.png", "figura": null, "nome": null, "confidenza": "alta", "scarto": true },
  { "file": "VER_029_06.png", "figura": null, "nome": null, "confidenza": "alta", "scarto": true },

  { "file": "VER_030_01.png", "figura": "249", "nome": "Segnale di direzione a freccia (fondo blu)", "confidenza": "media", "scarto": false },
  { "file": "VER_030_02.png", "figura": null, "nome": null, "confidenza": "alta", "scarto": true },

  { "file": "VER_031_01.png", "figura": "257", "nome": "Identificazione autostrada", "confidenza": "alta", "scarto": false },
  { "file": "VER_031_02.png", "figura": "256", "nome": "Identificazione itinerario internazionale europeo", "confidenza": "alta", "scarto": false },
  { "file": "VER_031_03.png", "figura": "258", "nome": "Identificazione strada statale", "confidenza": "alta", "scarto": false },
  { "file": "VER_031_04.png", "figura": "259", "nome": "Identificazione strada provinciale", "confidenza": "alta", "scarto": false },
  { "file": "VER_031_05.png", "figura": "260", "nome": "Identificazione strada comunale", "confidenza": "alta", "scarto": false },
  { "file": "VER_031_06.png", "figura": null, "nome": null, "confidenza": "alta", "scarto": true },
  { "file": "VER_031_07.png", "figura": null, "nome": null, "confidenza": "alta", "scarto": true },
  { "file": "VER_031_08.png", "figura": null, "nome": null, "confidenza": "alta", "scarto": true },
  { "file": "VER_031_09.png", "figura": null, "nome": null, "confidenza": "alta", "scarto": true },

  { "file": "VER_032_01.png", "figura": "273", "nome": "Inizio centro abitato", "confidenza": "alta", "scarto": false },
  { "file": "VER_032_02.png", "figura": "274", "nome": "Fine centro abitato", "confidenza": "alta", "scarto": false },
  { "file": "VER_032_03.png", "figura": null, "nome": null, "confidenza": "alta", "scarto": true },
  { "file": "VER_032_04.png", "figura": null, "nome": null, "confidenza": "alta", "scarto": true },
  { "file": "VER_032_05.png", "figura": null, "nome": null, "confidenza": "alta", "scarto": true },
  { "file": "VER_032_06.png", "figura": null, "nome": null, "confidenza": "alta", "scarto": true },
  { "file": "VER_032_07.png", "figura": null, "nome": null, "confidenza": "alta", "scarto": true },
  { "file": "VER_032_08.png", "figura": null, "nome": null, "confidenza": "alta", "scarto": true },

  { "file": "VER_033_01.png", "figura": "272", "nome": "Preavviso di uscita con indicazione delle località e distanza", "confidenza": "media", "scarto": false },
  { "file": "VER_033_02.png", "figura": "274", "nome": "Fine centro abitato con indicazione delle distanze", "confidenza": "media", "scarto": false },
  { "file": "VER_033_03.png", "figura": "275", "nome": "Confine di regione", "confidenza": "media", "scarto": false },
  { "file": "VER_033_04.png", "figura": "276", "nome": "Confine di provincia", "confidenza": "media", "scarto": false },
  { "file": "VER_033_05.png", "figura": "277", "nome": "Pronto soccorso", "confidenza": "media", "scarto": false },
  { "file": "VER_033_06.png", "figura": "278", "nome": "Stazione ferroviaria", "confidenza": "media", "scarto": false },
  { "file": "VER_033_07.png", "figura": "279", "nome": "Polizia", "confidenza": "media", "scarto": false },
  { "file": "VER_033_08.png", "figura": "280", "nome": "Carabinieri", "confidenza": "media", "scarto": false },
  { "file": "VER_033_09.png", "figura": "281", "nome": "Ufficio informazioni turistiche", "confidenza": "alta", "scarto": false },
  { "file": "VER_033_10.png", "figura": "282", "nome": "Ospedale", "confidenza": "alta", "scarto": false },
  { "file": "VER_033_11.png", "figura": "283", "nome": "Stemma comunale (municipio)", "confidenza": "alta", "scarto": false },
  { "file": "VER_033_12.png", "figura": "284", "nome": "Pittogramma copricapo/casco — presumibile Polizia municipale", "confidenza": "bassa", "scarto": false },
  { "file": "VER_033_13.png", "figura": "285", "nome": "Segnale di conferma con distanze delle località (autostrada)", "confidenza": "media", "scarto": false },
  { "file": "VER_033_14.png", "figura": "286", "nome": "Segnale di conferma con identificazione autostrada e freccia", "confidenza": "media", "scarto": false },
  { "file": "VER_033_15.png", "figura": null, "nome": "Strada soggetta a controllo elettronico della velocità", "confidenza": "alta", "scarto": false },
  { "file": "VER_033_16.png", "figura": null, "nome": "Velocità controllata elettronicamente — Polizia Municipale", "confidenza": "alta", "scarto": false },
  { "file": "VER_033_17.png", "figura": null, "nome": "Area soggetta a videosorveglianza", "confidenza": "alta", "scarto": false },

  { "file": "VER_034_01.png", "figura": "II 291", "nome": "Segnale nome-strada applicato in angolo", "confidenza": "alta", "scarto": false },
  { "file": "VER_034_02.png", "figura": "II 290", "nome": "Segnale nome-strada applicato a palo semaforico", "confidenza": "alta", "scarto": false },
  { "file": "VER_034_03.png", "figura": null, "nome": "Palo a bandiera Ø 60 zincato a caldo con 3 fascette e bulloneria", "confidenza": "alta", "scarto": false },
  { "file": "VER_034_04.png", "figura": "292", "nome": "Targa nome-strada piana con fori per fissaggio a parete o a palo a bandiera", "confidenza": "alta", "scarto": false },
  { "file": "VER_034_05.png", "figura": "292", "nome": "Targa nome-strada scatolata con attacchi saldati sul retro per fissaggio al palo", "confidenza": "alta", "scarto": false },
  { "file": "VER_034_06.png", "figura": "292", "nome": "Targa nome-strada in estruso con tappo di chiusura e staffone", "confidenza": "alta", "scarto": false },

  { "file": "VER_035_01.png", "figura": "298", "nome": "Preavviso di servizi turistici (informazioni e albergo) con distanza", "confidenza": "media", "scarto": false },
  { "file": "VER_035_02.png", "figura": "299", "nome": "Segnale di indicazione alberghi con elenco", "confidenza": "media", "scarto": false },
  { "file": "VER_035_03.png", "figura": "300", "nome": "Segnale di indicazione alberghi con direzioni", "confidenza": "media", "scarto": false },
  { "file": "VER_035_04.png", "figura": "301", "nome": "Segnali di direzione per alberghi (serie frecce)", "confidenza": "media", "scarto": false },

  { "file": "VER_036_01.png", "figura": "295", "nome": "Segnale di indicazione di corso d'acqua (fiume)", "confidenza": "media", "scarto": false },
  { "file": "VER_036_02.png", "figura": "302", "nome": "Ospedale", "confidenza": "alta", "scarto": false },
  { "file": "VER_036_03.png", "figura": "303", "nome": "Attraversamento pedonale", "confidenza": "alta", "scarto": false },
  { "file": "VER_036_04.png", "figura": "304", "nome": "Attraversamento pedonale scolastico (fondo arancione fluorescente)", "confidenza": "media", "scarto": false },
  { "file": "VER_036_05.png", "figura": "305", "nome": "SOS (punto di soccorso)", "confidenza": "alta", "scarto": false },
  { "file": "VER_036_06.png", "figura": "306", "nome": "Sottopassaggio pedonale", "confidenza": "media", "scarto": false },
  { "file": "VER_036_07.png", "figura": "307", "nome": "Sovrappassaggio pedonale", "confidenza": "media", "scarto": false },
  { "file": "VER_036_08.png", "figura": "308", "nome": "Passaggio pedonale su rampa inclinata", "confidenza": "bassa", "scarto": false },
  { "file": "VER_036_09.png", "figura": "309", "nome": "Strada senza uscita", "confidenza": "alta", "scarto": false },
  { "file": "VER_036_10.png", "figura": "310", "nome": "Preavviso di strada senza uscita", "confidenza": "media", "scarto": false },
  { "file": "VER_036_11.png", "figura": "311", "nome": "Preavviso di strada laterale senza uscita", "confidenza": "media", "scarto": false },
  { "file": "VER_036_12.png", "figura": "312", "nome": "Velocità consigliata", "confidenza": "alta", "scarto": false },
  { "file": "VER_036_13.png", "figura": "313", "nome": "Fine velocità consigliata", "confidenza": "alta", "scarto": false },
  { "file": "VER_036_14.png", "figura": "314", "nome": "Strada riservata ai veicoli a motore", "confidenza": "media", "scarto": false },
  { "file": "VER_036_15.png", "figura": "315", "nome": "Fine strada riservata ai veicoli a motore", "confidenza": "media", "scarto": false },
  { "file": "VER_036_16.png", "figura": "316", "nome": "Galleria", "confidenza": "media", "scarto": false },
  { "file": "VER_036_17.png", "figura": "317", "nome": "Fine galleria", "confidenza": "media", "scarto": false },
  { "file": "VER_036_18.png", "figura": "318", "nome": "Zona residenziale", "confidenza": "media", "scarto": false },
  { "file": "VER_036_19.png", "figura": "319", "nome": "Fine zona residenziale", "confidenza": "media", "scarto": false },
  { "file": "VER_036_20.png", "figura": "320", "nome": "Area pedonale", "confidenza": "alta", "scarto": false },
  { "file": "VER_036_21.png", "figura": "321", "nome": "Fine area pedonale", "confidenza": "alta", "scarto": false },
  { "file": "VER_036_22.png", "figura": "322/A", "nome": "Zona a traffico limitato", "confidenza": "alta", "scarto": false },
  { "file": "VER_036_23.png", "figura": "322/B", "nome": "Fine zona a traffico limitato", "confidenza": "alta", "scarto": false },
  { "file": "VER_036_24.png", "figura": "323/A", "nome": "Zona a velocità limitata (Zona 30)", "confidenza": "alta", "scarto": false },
  { "file": "VER_036_25.png", "figura": "323/B", "nome": "Fine zona a velocità limitata", "confidenza": "alta", "scarto": false },
  { "file": "VER_036_26.png", "figura": "324", "nome": "Pista ciclabile", "confidenza": "media", "scarto": false },
  { "file": "VER_036_27.png", "figura": "320/P", "nome": "Pannello integrativo area pedonale con elenco eccezioni", "confidenza": "media", "scarto": false },
  { "file": "VER_036_28.png", "figura": "325", "nome": "Schema di itinerario urbano con percorso indicato da freccia", "confidenza": "bassa", "scarto": false },
  { "file": "VER_036_29.png", "figura": "322/A/P", "nome": "Pannello integrativo zona a traffico limitato con divieti ed eccezioni", "confidenza": "media", "scarto": false },
  { "file": "VER_036_30.png", "figura": "326", "nome": "Schema di itinerario urbano con percorso indicato da freccia (variante)", "confidenza": "bassa", "scarto": false },
  { "file": "VER_036_31.png", "figura": "327", "nome": "Strada extraurbana principale", "confidenza": "alta", "scarto": false },

  { "file": "VER_038_01.png", "figura": "345", "nome": "Autostrada", "confidenza": "alta", "scarto": false },
  { "file": "VER_038_02.png", "figura": "346", "nome": "Fine autostrada", "confidenza": "alta", "scarto": false },
  { "file": "VER_038_03.png", "figura": "347", "nome": "Autostrada con pannello dei divieti", "confidenza": "media", "scarto": false }
]
